[
  { "inputs": [], "stateMutability": "nonpayable", "type": "constructor" },
  {
    "inputs": [],
    "name": "connectors",
    "outputs": [{ "internalType": "address", "name": "", "type": "address" }],
    "stateMutability": "view",
    "type": "function"
  },
  {
    "inputs": [{ "internalType": "uint64", "name": "id", "type": "uint64" }],
    "name": "getAccount",
    "outputs": [
      { "internalType": "address", "name": "account", "type": "address" }
    ],
    "stateMutability": "view",
    "type": "function"
  },
  {
    "inputs": [
      { "internalType": "address", "name": "account", "type": "address" }
    ],
    "name": "getAccountAuthorities",
    "outputs": [
      { "internalType": "address[]", "name": "", "type": "address[]" }
    ],
    "stateMutability": "view",
    "type": "function"
  },
  {
    "inputs": [
      { "internalType": "address[]", "name": "accounts", "type": "address[]" }
    ],
    "name": "getAccountVersions",
    "outputs": [
      { "internalType": "uint256[]", "name": "", "type": "uint256[]" }
    ],
    "stateMutability": "view",
    "type": "function"
  },
  {
    "inputs": [],
    "name": "getEnabledConnectores",
    "outputs": [
      { "internalType": "uint256", "name": "", "type": "uint256" },
      { "internalType": "address[]", "name": "", "type": "address[]" }
    ],
    "stateMutability": "view",
    "type": "function"
  },
  {
    "inputs": [
      { "internalType": "address", "name": "account", "type": "address" }
    ],
    "name": "getID",
    "outputs": [{ "internalType": "uint256", "name": "id", "type": "uint256" }],
    "stateMutability": "view",
    "type": "function"
  },
  {
    "inputs": [{ "internalType": "uint256", "name": "id", "type": "uint256" }],
    "name": "getIDAuthorities",
    "outputs": [
      { "internalType": "address[]", "name": "", "type": "address[]" }
    ],
    "stateMutability": "view",
    "type": "function"
  },
  {
    "inputs": [
      { "internalType": "address", "name": "authority", "type": "address" }
    ],
    "name": "getAuthorityAccounts",
    "outputs": [
      { "internalType": "address[]", "name": "", "type": "address[]" }
    ],
    "stateMutability": "view",
    "type": "function"
  },
  {
    "inputs": [
      { "internalType": "address", "name": "authority", "type": "address" }
    ],
    "name": "getAuthorityDetails",
    "outputs": [
      {
        "components": [
          { "internalType": "uint64[]", "name": "IDs", "type": "uint64[]" },
          {
            "internalType": "address[]",
            "name": "accounts",
            "type": "address[]"
          },
          {
            "internalType": "uint256[]",
            "name": "versions",
            "type": "uint256[]"
          }
        ],
        "name": "",
        "type": "tuple"
      }
    ],
    "stateMutability": "view",
    "type": "function"
  },
  {
    "inputs": [
      { "internalType": "address", "name": "authority", "type": "address" }
    ],
    "name": "getAuthorityIDs",
    "outputs": [{ "internalType": "uint64[]", "name": "", "type": "uint64[]" }],
    "stateMutability": "view",
    "type": "function"
  },
  {
    "inputs": [],
    "name": "getStaticConnectores",
    "outputs": [
      { "internalType": "address[]", "name": "", "type": "address[]" }
    ],
    "stateMutability": "view",
    "type": "function"
  },
  {
    "inputs": [],
    "name": "index",
    "outputs": [{ "internalType": "address", "name": "", "type": "address" }],
    "stateMutability": "view",
    "type": "function"
  },
  {
    "inputs": [],
    "name": "list",
    "outputs": [{ "internalType": "address", "name": "", "type": "address" }],
    "stateMutability": "view",
    "type": "function"
  },
  {
    "inputs": [],
    "name": "name",
    "outputs": [{ "internalType": "string", "name": "", "type": "string" }],
    "stateMutability": "view",
    "type": "function"
  },
  {
    "inputs": [],
    "name": "version",
    "outputs": [{ "internalType": "uint256", "name": "", "type": "uint256" }],
    "stateMutability": "view",
    "type": "function"
  },
  {
    "inputs": [
      {
        "internalType": "uint256",
        "name": "id",
        "type": "uint256"
      }
    ],
    "name": "getAccountDetails",
    "outputs": [
      {
        "components": [
          {
            "internalType": "uint256",
            "name": "ID",
            "type": "uint256"
          },
          {
            "internalType": "address",
            "name": "account",
            "type": "address"
          },
          {
            "internalType": "uint256",
            "name": "version",
            "type": "uint256"
          },
          {
            "internalType": "address[]",
            "name": "authorities",
            "type": "address[]"
          }
        ],
        "internalType": "struct AccountResolver.AccountData",
        "name": "",
        "type": "tuple"
      }
    ],
    "stateMutability": "view",
    "type": "function"
  }
]
